cnloc/__init__.py
cnloc/data/location_year_20251201.csv
cnloc-0.1.7.dist-info/licenses/LICENSE
cnloc-0.1.7.dist-info/METADATA
cnloc-0.1.7.dist-info/WHEEL
cnloc-0.1.7.dist-info/top_level.txt
cnloc-0.1.7.dist-info/RECORD
